full_match/__init__.py
full_match/match.py
full_match/py.typed
full_match-0.0.3.dist-info/LICENSE
full_match-0.0.3.dist-info/METADATA
full_match-0.0.3.dist-info/WHEEL
full_match-0.0.3.dist-info/top_level.txt
full_match-0.0.3.dist-info/RECORD
